ftoml/__init__.py
ftoml-0.2.0.dist-info/LICENSE
ftoml-0.2.0.dist-info/METADATA
ftoml-0.2.0.dist-info/WHEEL
ftoml-0.2.0.dist-info/top_level.txt
ftoml-0.2.0.dist-info/RECORD
