Metadata-Version: 2.1
Name: ftoml
Version: 0.2.0
Summary: Python library unifying f-stringswith Tom's Obvious, Minimal Language
Home-page: https://github.com/schuellerf/ftoml
Author: Florian Schüller
Author-email: florian.schueller@gmail.com
License: MIT
Platform: UNKNOWN
Classifier: Development Status :: 5 - Production/Stable
Classifier: Intended Audience :: Developers
Classifier: License :: OSI Approved :: MIT License
Classifier: Operating System :: OS Independent
Classifier: Programming Language :: Python
Requires-Python: >=2.6, !=3.0.*, !=3.1.*, !=3.2.*
Requires-Dist: toml
Requires-Dist: fstring
Requires-Dist: astroid
